{"rows":[{"columns":[{"size":"col-sm-6","containers":[{"genType":"container","proprieties":{"tag":"iden","type":"sectionheader","text":"<p>Identify</p>\n","maxlength":40},"fields":[],"style":{"id":"","class":"","inline":""},"options":{"autoTag":false},"id":"sectionheader1583837160857","xsl":{"useDefault":true}}]},{"size":"col-sm-6","containers":[{"genType":"container","proprieties":{"tag":"toolsbar_1","type":"toolsbar","align":" pull-right","btnSize":"","style":"default","vertical":true,"dynamic":false,"outline":false},"fields":[{"properties":{"_id":"button_a7fd_fc9c","label":"Gravar","tag":"gravar_idt","name":"p_gravar_idt","type":"button","target":"confirm","request_fields":[],"target_fields":"","closerefresh":false,"refresh_components":[],"refresh_submit":false,"action":"Mapas_form","service":{"code":"","desc":"","proc":"","connectionsReq":[],"fieldsReq":[],"connectionsRes":[],"fieldsRes":[]},"transaction":false,"custom_return":false,"class":"success","iconColor":"#333","iconClass":"","img":"fa-save"},"style":{"id":"","class":"","inline":""},"options":{"autoTag":false,"rules":[]},"xsl":{"useDefault":true,"template":false},"validation":[]}],"style":{"id":"","class":"","inline":""},"options":{"autoTag":false},"id":"toolsbar1583837165171","xsl":{"useDefault":true}}]}],"propreties":{"class":""}},{"columns":[{"size":"col-sm-12","containers":[{"genType":"container","proprieties":{"title":"Separatorlist","tag":"separatorlist_1","hasTitle":false,"collapsible":false,"type":"separatorlist","dialog":false,"ordertable":false,"countRow":false,"countHeader":false,"collapsed":false},"fields":[{"properties":{"_id":"select_3a92_b706","label":"Layer","tag":"layer_idt","name":"p_layer_idt","type":"select","multiple":false,"tags":false,"domain_value":[],"domain":"","maxlength":250,"required":false,"change":false,"disabled":false,"size":"3","right":false,"java-type":"","visible":true},"style":{"id":"","class":"","inline":""},"options":{"autoTag":false,"rules":[]},"xsl":{"useDefault":true,"template":false},"validation":[]},{"properties":{"_id":"text_b298_8700","label":"Label","tag":"label_idf","name":"p_label_idf","type":"text","maxlength":250,"required":false,"change":false,"readonly":false,"disabled":false,"placeholder":"","desclabel":false,"size":"3","right":false,"visible":true},"style":{"id":"","class":"","inline":""},"options":{"autoTag":false,"rules":[]},"xsl":{"useDefault":true,"template":false},"validation":[]},{"properties":{"_id":"number_a767_b7ac","label":"Ordem","tag":"ordem_idf","name":"p_ordem_idf","type":"number","min":"","max":"","maxlength":250,"required":false,"change":false,"readonly":false,"disabled":false,"placeholder":"","desclabel":false,"size":"3","right":false,"java-type":"","visible":true},"style":{"id":"","class":"","inline":""},"options":{"autoTag":false,"rules":[]},"xsl":{"useDefault":true,"template":false},"validation":[]},{"properties":{"_id":"select_f89c_b3bc","label":"Campo","tag":"campo_idf","name":"p_campo_idf","type":"select","multiple":false,"tags":false,"domain_value":[],"domain":"","maxlength":250,"required":false,"change":false,"disabled":false,"size":"3","right":false,"java-type":"","visible":true},"style":{"id":"","class":"","inline":""},"options":{"autoTag":false,"rules":[]},"xsl":{"useDefault":true,"template":false},"validation":[]},{"properties":{"_id":"select_422a_b145","label":"Editavel","tag":"editavel_ed","name":"p_editavel_ed","type":"select","multiple":false,"tags":false,"domain_value":[],"domain":"","maxlength":250,"required":false,"change":false,"disabled":false,"size":"3","right":false,"java-type":"","visible":true},"style":{"id":"","class":"","inline":""},"options":{"autoTag":false,"rules":[]},"xsl":{"useDefault":true,"template":false},"validation":[]}],"style":{"id":"","class":"","inline":""},"options":{"autoTag":false},"id":"separatorlist1583837433820","xsl":{"useDefault":true}}]}],"propreties":{"class":""}}],"plsql":{"instance":"","table":"","package":"nosi.webapps.poser_2020.pages","html":"Infowindow_geoserver","gentype":"java","replace":false,"label":false,"biztalk":false,"process":false,"subversionpath":""},"css":"","js":"","files":{"css":[],"js":[],"xsl":[]},"blocklyData":"<xml><block type=\"controller\" id=\"controller\" x=\"388\" y=\"13\"></block></xml>"}
